MANIFEST.in
README.txt
setup.py
docs/HISTORY.txt
silva/__init__.py
silva.pageactions.printfriendly.egg-info/PKG-INFO
silva.pageactions.printfriendly.egg-info/SOURCES.txt
silva.pageactions.printfriendly.egg-info/dependency_links.txt
silva.pageactions.printfriendly.egg-info/namespace_packages.txt
silva.pageactions.printfriendly.egg-info/not-zip-safe
silva.pageactions.printfriendly.egg-info/requires.txt
silva.pageactions.printfriendly.egg-info/top_level.txt
silva/pageactions/__init__.py
silva/pageactions/printfriendly/__init__.py
silva/pageactions/printfriendly/configure.zcml
silva/pageactions/printfriendly/printfriendly.py
silva/pageactions/printfriendly/printfriendly_templates/printaction.cpt
silva/pageactions/printfriendly/printfriendly_templates/printfriendly.pt