Metadata-Version: 1.1
Name: silva.pageactions.printfriendly
Version: 1.0.2
Summary: Display a simple printable version of the content in Silva CMS
Home-page: https://github.com/silvacms/silva.pageactions.printfriendly
Author: Infrae
Author-email: info@infrae.com
License: BSD
Keywords: silva pageactions print
Platform: UNKNOWN
Classifier: Framework :: Zope2
Classifier: Programming Language :: Python
Classifier: Topic :: Software Development :: Libraries :: Python Modules
